LineToolkit.py
README.md
setup.py
LineToolkit.egg-info/PKG-INFO
LineToolkit.egg-info/SOURCES.txt
LineToolkit.egg-info/dependency_links.txt
LineToolkit.egg-info/top_level.txt