Metadata-Version: 2.1
Name: LineToolkit
Version: 0.0.2
Summary: Some simple tools for Line Notify API
Home-page: https://github.com/kirin-lin/LineToolkit
Author: Kirin Lin
Author-email: chilin.lin@gmail.com
License: UNKNOWN
Platform: UNKNOWN
